pywargame/__init__.py
pywargame/common/__init__.py
pywargame/common/collector.py
pywargame/common/dicedraw.py
pywargame/common/drawdice.py
pywargame/common/singleton.py
pywargame/common/test.py
pywargame/common/verbose.py
pywargame/common/verboseguard.py
pywargame/cyberboard/__init__.py
pywargame/cyberboard/archive.py
pywargame/cyberboard/base.py
pywargame/cyberboard/board.py
pywargame/cyberboard/cell.py
pywargame/cyberboard/collect.py
pywargame/cyberboard/collectgbx0pwd.py
pywargame/cyberboard/collectgbxext.py
pywargame/cyberboard/collectgsnexp.py
pywargame/cyberboard/collectgsnext.py
pywargame/cyberboard/draw.py
pywargame/cyberboard/exporter.py
pywargame/cyberboard/extractor.py
pywargame/cyberboard/features.py
pywargame/cyberboard/gamebox.py
pywargame/cyberboard/gbxexp.py
pywargame/cyberboard/gbxext.py
pywargame/cyberboard/gsnexp.py
pywargame/cyberboard/gsnext.py
pywargame/cyberboard/head.py
pywargame/cyberboard/image.py
pywargame/cyberboard/main.py
pywargame/cyberboard/mark.py
pywargame/cyberboard/palette.py
pywargame/cyberboard/piece.py
pywargame/cyberboard/player.py
pywargame/cyberboard/scenario.py
pywargame/cyberboard/testgrid.py
pywargame/cyberboard/tile.py
pywargame/cyberboard/tray.py
pywargame/cyberboard/windows.py
pywargame/cyberboard/zeropwd.py
pywargame/latex/__init__.py
pywargame/latex/collect.py
pywargame/latex/latexexporter.py
pywargame/latex/main.py
pywargame/vassal/__init__.py
pywargame/vassal/base.py
pywargame/vassal/board.py
pywargame/vassal/buildfile.py
pywargame/vassal/chart.py
pywargame/vassal/chessclock.py
pywargame/vassal/collect.py
pywargame/vassal/collectdump.py
pywargame/vassal/collectmrg.py
pywargame/vassal/collectpatch.py
pywargame/vassal/command.py
pywargame/vassal/documentation.py
pywargame/vassal/dumpvsav.py
pywargame/vassal/element.py
pywargame/vassal/exporter.py
pywargame/vassal/extension.py
pywargame/vassal/folder.py
pywargame/vassal/game.py
pywargame/vassal/gameelements.py
pywargame/vassal/globalkey.py
pywargame-0.5.4.dist-info/licenses/LICENSE
pywargame-0.5.4.dist-info/METADATA
pywargame-0.5.4.dist-info/WHEEL
pywargame-0.5.4.dist-info/entry_points.txt
pywargame-0.5.4.dist-info/top_level.txt
pywargame-0.5.4.dist-info/RECORD
