Metadata-Version: 2.4
Name: pywargame
Version: 0.5.4
Summary: Python library to manipulate wargame modules
Home-page: https://wargames_tex.gitlab.io/pywargame/
Author: Christian Holm Christensen
Author-email: cholmcc@gmail.com
License: CC-BY-SA-4.0
Project-URL: Documentation, https://wargames_tex.gitlab.io/pywargame
Project-URL: Source Code, https://gitlab.com/wargmes_tex/pywargame
Keywords: Boardgame,Wargame,VASSAL,ZunTzu,CyberBoard,LaTeX
Classifier: Programming Language :: Python :: 3
Classifier: Intended Audience :: Developers
Classifier: Intended Audience :: Other Audience
Classifier: Topic :: Games/Entertainment :: Board Games
Requires-Python: >=3.6
License-File: LICENSE
Requires-Dist: numpy>=1.16
Requires-Dist: pillow>=10.0.0
Requires-Dist: svgwrite>=1.3.0
Requires-Dist: wand>=0.6.0
Requires-Dist: myst-parser>=4.0.0
Dynamic: license-file
